mylassi_xyz_lib/__init__.py
mylassi_xyz_lib/api_client.py
mylassi_xyz_lib/schemas/__init__.py
mylassi_xyz_lib/schemas/apiv2.py
mylassi_xyz_lib/schemas/documents.py
mylassi_xyz_lib/schemas/lesson_page_elements.py
mylassi_xyz_lib/schemas/lesson_pages.py
mylassi_xyz_lib/schemas/lessons.py
mylassi_xyz_lib/schemas/tags.py
mylassi_xyz_lib/schemas/users.py
mylassi_xyz_lib/services/__init__.py
mylassi_xyz_lib/services/document_service.py
school_mylassi_xyz-0.30.6.dist-info/METADATA
school_mylassi_xyz-0.30.6.dist-info/WHEEL
school_mylassi_xyz-0.30.6.dist-info/entry_points.txt
school_mylassi_xyz-0.30.6.dist-info/top_level.txt
school_mylassi_xyz-0.30.6.dist-info/RECORD
